obj_mpp/__init__.py
obj_mpp/version.py
obj_mpp/app/detection_cli.py
obj_mpp/app/doc_object_qualities.py
obj_mpp/app/doc_object_types.py
obj_mpp/app/doc_search.py
obj_mpp/catalog/input/numpy_.py
obj_mpp/catalog/input/skimage_.py
obj_mpp/catalog/output/dim2.py
obj_mpp/catalog/output/dim3.py
obj_mpp/catalog/output/dimX.py
obj_mpp/catalog/quality/contour.py
obj_mpp/catalog/quality/contrast.py
obj_mpp/catalog/quality/gradient.py
obj_mpp/config/app.py
obj_mpp/constant/app.py
obj_mpp/constant/catalog.py
obj_mpp/constant/signal.py
obj_mpp/constant/config/definition.py
obj_mpp/constant/config/label.py
obj_mpp/constant/config/parameter.py
obj_mpp/constant/interface/message.py
obj_mpp/constant/interface/storage.py
obj_mpp/extension/function.py
obj_mpp/extension/importer.py
obj_mpp/interface/console/detection.py
obj_mpp/interface/storage/api.py
obj_mpp/interface/storage/save/detection.py
obj_mpp/interface/window/detection.py
obj_mpp/task/analysis/illustration.py
obj_mpp/task/analysis/signal.py
obj_mpp/task/catalog/importer.py
obj_mpp/task/catalog/specifier.py
obj_mpp/task/detection/multiple.py
obj_mpp/task/detection/parallel.py
obj_mpp/task/detection/sequential.py
obj_mpp/task/detection/single.py
obj_mpp/task/validation/interface.py
obj_mpp/task/validation/point.py
obj_mpp/type/detection.py
obj_mpp/type/exception.py
obj_mpp/type/quality/base.py
obj_mpp/type/signal/context.py
obj_mpp-2026.3.dist-info/METADATA
obj_mpp-2026.3.dist-info/WHEEL
obj_mpp-2026.3.dist-info/entry_points.txt
obj_mpp-2026.3.dist-info/top_level.txt
obj_mpp-2026.3.dist-info/RECORD
