Metadata-Version: 2.4
Name: obj.mpp
Version: 2026.3
Summary: Object/pattern detection using a Marked Point Process
Home-page: https://src.koda.cnrs.fr/eric.debreuve/Obj.MPP/
Author: Eric Debreuve
Author-email: eric.debreuve@cnrs.fr
License: CeCILL-2.1
Project-URL: Documentation, https://src.koda.cnrs.fr/eric.debreuve/Obj.MPP/-/wikis/home
Project-URL: Source, https://src.koda.cnrs.fr/eric.debreuve/Obj.MPP/
Keywords: image,signal,object detection,pattern detection,marked point process
Classifier: Topic :: Scientific/Engineering :: Image Recognition
Classifier: Intended Audience :: Science/Research
Classifier: License :: OSI Approved :: CEA CNRS Inria Logiciel Libre License, version 2.1 (CeCILL-2.1)
Classifier: Programming Language :: Python :: 3
Classifier: Development Status :: 4 - Beta
Requires-Python: >=3.11
Requires-Dist: Pillow
Requires-Dist: conf-ini-g
Requires-Dist: imageio
Requires-Dist: json-any
Requires-Dist: logger-36
Requires-Dist: matplotlib
Requires-Dist: mpss_tools_36
Requires-Dist: networkx
Requires-Dist: numpy
Requires-Dist: p-pattern
Requires-Dist: platformdirs
Requires-Dist: rich
Requires-Dist: scikit-image
Requires-Dist: scipy
Requires-Dist: value_factory
Dynamic: author
Dynamic: author-email
Dynamic: classifier
Dynamic: description
Dynamic: description-content-type
Dynamic: home-page
Dynamic: keywords
Dynamic: license
Dynamic: project-url
Dynamic: requires-dist
Dynamic: requires-python
Dynamic: summary
